dev_pipeline.py
livenodes/__init__.py
livenodes/graph.py
livenodes/node.py
livenodes/producer.py
livenodes/producer_async.py
livenodes/producer_blocking.py
livenodes/registry.py
livenodes/viewer.py
livenodes/components/__init__.py
livenodes/components/connection.py
livenodes/components/node_connector.py
livenodes/components/node_logger.py
livenodes/components/node_serializer.py
livenodes/components/port.py
livenodes/components/bridges/__init__.py
livenodes/components/bridges/bridge_abstract.py
livenodes/components/bridges/bridge_aioprocessing.py
livenodes/components/bridges/bridge_local.py
livenodes/components/bridges/bridge_process.py
livenodes/components/bridges/bridge_thread.py
livenodes/components/bridges/mp_data_storage.py
livenodes/components/computer/__init__.py
livenodes/components/computer/cmp_common.py
livenodes/components/computer/cmp_local.py
livenodes/components/computer/cmp_process.py
livenodes/components/computer/cmp_thread.py
livenodes/components/computer/utils.py
livenodes/components/utils/__init__.py
livenodes/components/utils/clock.py
livenodes/components/utils/perf.py
livenodes/components/utils/reportable.py
livenodes/components/utils/utils.py
livenodes-1.1.3.dist-info/licenses/AUTHORS.rst
livenodes-1.1.3.dist-info/licenses/LICENSE
livenodes-1.1.3.dist-info/METADATA
livenodes-1.1.3.dist-info/WHEEL
livenodes-1.1.3.dist-info/top_level.txt
livenodes-1.1.3.dist-info/zip-safe
livenodes-1.1.3.dist-info/RECORD
